AioFilters.py
aiofilters-1.0.0.dist-info/WHEEL
aiofilters-1.0.0.dist-info/METADATA
aiofilters-1.0.0.dist-info/RECORD
